python_project_cli/__init__.py
python_project_cli/main.py
python_project_cli-1.2.0.dist-info/LICENSE
python_project_cli-1.2.0.dist-info/METADATA
python_project_cli-1.2.0.dist-info/WHEEL
python_project_cli-1.2.0.dist-info/entry_points.txt
python_project_cli-1.2.0.dist-info/RECORD
