Metadata-Version: 2.1
Name: python_project_cli
Version: 1.2.0
Summary: CLI for building base djang and fastapi based projects
Home-page: https://github.com/MentorMate/python-project-cli/
Author: alexandermentormate
Requires-Python: >=3.11,<4.0
Classifier: License :: OSI Approved :: The Unlicense (Unlicense)
Classifier: Operating System :: OS Independent
Classifier: Programming Language :: Python :: 3
Classifier: Programming Language :: Python :: 3.11
Classifier: Programming Language :: Python :: 3.12
Requires-Dist: cookiecutter (>=2.6.0,<3.0.0)
Requires-Dist: typer (>=0.12.3,<0.13.0)
Project-URL: Changelog, https://github.com/MentorMate/python-project-cli/blob/main/CHANGELOG.md
Project-URL: Repository, https://github.com/MentorMate/python-project-cli/
